umls_similarity/__init__.py
umls_similarity/umls.py
umls_similarity/wordnet.py
umls_similarity/__pycache__/__init__.cpython-36.pyc
umls_similarity/__pycache__/umls.cpython-36.pyc
umls_similarity/__pycache__/wordnet.cpython-36.pyc
umls_similarity/scripts/__init__.py
umls_similarity/scripts/umls/utils/create-icfrequency.pl
umls_similarity/scripts/umls/utils/create-icpropagation.pl
umls_similarity/scripts/umls/utils/spearmans.pl
umls_similarity/scripts/umls/utils/umls-similarity.pl
umls_similarity/scripts/umls/utils/vector-input.pl
umls_similarity/scripts/wordnet/sample.pl
umls_similarity/scripts/wordnet/config-files/config-all.conf
umls_similarity/scripts/wordnet/config-files/config-hso.conf
umls_similarity/scripts/wordnet/config-files/config-jcn.conf
umls_similarity/scripts/wordnet/config-files/config-lch.conf
umls_similarity/scripts/wordnet/config-files/config-lesk.conf
umls_similarity/scripts/wordnet/config-files/config-lin.conf
umls_similarity/scripts/wordnet/config-files/config-path.conf
umls_similarity/scripts/wordnet/config-files/config-random.conf
umls_similarity/scripts/wordnet/config-files/config-res.conf
umls_similarity/scripts/wordnet/config-files/config-vector.conf
umls_similarity/scripts/wordnet/config-files/config-vector_pairs.conf
umls_similarity/scripts/wordnet/config-files/config-wup.conf
umls_similarity-0.0.2.dist-info/LICENSE
umls_similarity-0.0.2.dist-info/METADATA
umls_similarity-0.0.2.dist-info/WHEEL
umls_similarity-0.0.2.dist-info/top_level.txt
umls_similarity-0.0.2.dist-info/RECORD
